pattern_palette/PatternPalette.py
pattern_palette/__init__.py
PatternPalette-0.2.dist-info/METADATA
PatternPalette-0.2.dist-info/WHEEL
PatternPalette-0.2.dist-info/top_level.txt
PatternPalette-0.2.dist-info/RECORD
