Metadata-Version: 2.1
Name: PatternPalette
Version: 0.2
Summary: A Python package for generating various patterns.
Author: Aditya Srivastav
Author-email: adityathestar2006@gmail.com
Classifier: Programming Language :: Python :: 3
Classifier: Programming Language :: Python :: 3.6
Classifier: Programming Language :: Python :: 3.7
Classifier: Programming Language :: Python :: 3.8
Classifier: Programming Language :: Python :: 3.9
Classifier: License :: OSI Approved :: Apache Software License
Classifier: Operating System :: OS Independent
Requires-Python: >=3.6
